disc_tool/__init__.py
disc_tool/cli.py
disc_tool/discord_client.py
disc_tool/social_graph.py
disc_tool-0.1.0.dist-info/entry_points.txt
disc_tool-0.1.0.dist-info/LICENSE
disc_tool-0.1.0.dist-info/WHEEL
disc_tool-0.1.0.dist-info/METADATA
disc_tool-0.1.0.dist-info/RECORD
